geci_plots/__init__.py
geci_plots/boxplots.py
geci_plots/cli.py
geci_plots/geci_plots.py
geci_plots/plot_kernel_density_gls.py
geci_plots-0.8.0.dist-info/entry_points.txt
geci_plots-0.8.0.dist-info/licenses/LICENSE
geci_plots-0.8.0.dist-info/WHEEL
geci_plots-0.8.0.dist-info/METADATA
geci_plots-0.8.0.dist-info/RECORD
