Metadata-Version: 2.4
Name: geci_plots
Version: 0.8.0
Summary: A custom matplotlib module
Home-page: https://github.com/IslasGECI/geci_plots
Author: Ciencia de Datos • GECI
Author-email: ciencia.datos@islas.org.mx
Requires-Python: >=3.9
Classifier: License :: OSI Approved :: GNU General Public License v3 or later (GPLv3+)
License-File: LICENSE
Requires-Dist: geoambiental
Requires-Dist: geopandas
Requires-Dist: matplotlib
Requires-Dist: numpy
Requires-Dist: pandas
Requires-Dist: typer[all]
